nonebot_plugin_overbracket/__init__.py
nonebot_plugin_overbracket/config.py
nonebot_plugin_overbracket-0.2.0.dist-info/LICENSE
nonebot_plugin_overbracket-0.2.0.dist-info/METADATA
nonebot_plugin_overbracket-0.2.0.dist-info/WHEEL
nonebot_plugin_overbracket-0.2.0.dist-info/top_level.txt
nonebot_plugin_overbracket-0.2.0.dist-info/RECORD
