Metadata-Version: 2.1
Name: nonebot-plugin-overbracket
Version: 0.2.0
Summary: NoneBot2 插件 通括膨胀——泛滥的括号
Author-email: HivertMoZara <worldmozara@163.com>
License: MIT
Project-URL: Homepage, https://github.com/NCBM/nonebot-plugin-overbracket
Project-URL: Repository, https://github.com/NCBM/nonebot-plugin-overbracket
Requires-Python: >=3.8
License-File: LICENSE
Requires-Dist: nonebot2 >=2.2.0
